sl_transit_repl/__init__.py
sl_transit_repl/__main__.py
sl_transit_repl/main.py
sl_transit_repl-0.1.1.dist-info/METADATA
sl_transit_repl-0.1.1.dist-info/WHEEL
sl_transit_repl-0.1.1.dist-info/entry_points.txt
sl_transit_repl-0.1.1.dist-info/licenses/LICENSE
sl_transit_repl-0.1.1.dist-info/RECORD
