Metadata-Version: 2.4
Name: sl-transit-repl
Version: 0.1.1
Summary: A REPL for querying real time departure data for Stockholm's public transit system (SL) via Trafiklab APIs.
Project-URL: Homepage, https://github.com/abonhomme/sl_transit_repl
Project-URL: Repository, https://github.com/abonhomme/sl_transit_repl.git
Project-URL: Issues, https://github.com/abonhomme/sl_transit_repl/issues
Author-email: Arjumand Bonhomme <841604+abonhomme@users.noreply.github.com>
License-Expression: MIT
License-File: LICENSE
Keywords: SL,metro,pendeltåg,stockholm,storstockholms lokaltrafik,subway,t-bana,tbana,trafiklab,transit,tunnelbana
Classifier: Development Status :: 4 - Beta
Classifier: Intended Audience :: End Users/Desktop
Classifier: License :: OSI Approved :: MIT License
Classifier: Operating System :: OS Independent
Classifier: Programming Language :: Python :: 3
Classifier: Programming Language :: Python :: 3.11
Classifier: Programming Language :: Python :: 3.12
Classifier: Topic :: Software Development :: Libraries :: Python Modules
Classifier: Topic :: Utilities
Requires-Python: >=3.11
Requires-Dist: prompt-toolkit>=3.0.52
Requires-Dist: requests>=2.32.5
Requires-Dist: rich>=14.1.0
Requires-Dist: unidecode>=1.4.0
Provides-Extra: dev
Requires-Dist: pytest-cov>=6.0.0; extra == 'dev'
Requires-Dist: pytest>=8.0.0; extra == 'dev'
Requires-Dist: ruff>=0.8.0; extra == 'dev'
